nnresample/__init__.py
nnresample/nnresample.py
nnresample/utility.py
nnresample-0.2.4.1.dist-info/LICENSE
nnresample-0.2.4.1.dist-info/METADATA
nnresample-0.2.4.1.dist-info/WHEEL
nnresample-0.2.4.1.dist-info/top_level.txt
nnresample-0.2.4.1.dist-info/RECORD
